datamart_rest/__init__.py
datamart_rest/rest.py
datamart_rest-0.2.7.dist-info/LICENSE.txt
datamart_rest-0.2.7.dist-info/METADATA
datamart_rest-0.2.7.dist-info/WHEEL
datamart_rest-0.2.7.dist-info/top_level.txt
datamart_rest-0.2.7.dist-info/RECORD
