Metadata-Version: 2.1
Name: datamart-rest
Version: 0.2.7
Summary: Client library for DataMart's REST API
Home-page: https://gitlab.com/datadrivendiscovery/datamart-api
Author: Remi Rampin, Fernando Chirigati
Author-email: remi.rampin@nyu.edu, fchirigati@nyu.edu
Maintainer: Remi Rampin, Fernando Chirigati
Maintainer-email: remi.rampin@nyu.edu, fchirigati@nyu.edu
License: BSD-3-Clause
Project-URL: Homepage, https://gitlab.com/datadrivendiscovery/datamart-api
Project-URL: Source, https://gitlab.com/datadrivendiscovery/datamart-api
Project-URL: Tracker, https://gitlab.com/datadrivendiscovery/datamart-api/issues
Keywords: datamart,rest,auctus
Platform: UNKNOWN
Classifier: Development Status :: 4 - Beta
Classifier: Intended Audience :: Science/Research
Classifier: Operating System :: OS Independent
Classifier: Programming Language :: Python :: 3
Classifier: Topic :: Internet :: WWW/HTTP :: Indexing/Search
Classifier: Topic :: Scientific/Engineering :: Information Analysis
Requires-Dist: d3m
Requires-Dist: datamart (==2021.3.17)
Requires-Dist: requests
Requires-Dist: websocket-client
